cerebras_agent/__init__.py
cerebras_agent/agent.py
cerebras_agent/cli.py
cerebras_agent/file_ops.py
cerebras_agent-0.1.0.dist-info/licenses/LICENSE
cerebras_agent-0.1.0.dist-info/METADATA
cerebras_agent-0.1.0.dist-info/WHEEL
cerebras_agent-0.1.0.dist-info/entry_points.txt
cerebras_agent-0.1.0.dist-info/top_level.txt
cerebras_agent-0.1.0.dist-info/RECORD
