Metadata-Version: 2.4
Name: cerebras-agent
Version: 0.1.0
Summary: A local agent for code development using Cerebras API
Home-page: https://github.com/cerebras/cerebras-coding-agent
Author: Cerebras
Author-email: Cerebras <info@cerebras.net>
License: MIT
Project-URL: Homepage, https://github.com/jio-gl/cerebras-coding-agent
Project-URL: Issues, https://github.com/jio-gl/cerebras-coding-agent/issues
Classifier: Development Status :: 3 - Alpha
Classifier: Intended Audience :: Developers
Classifier: License :: OSI Approved :: MIT License
Classifier: Programming Language :: Python :: 3
Classifier: Programming Language :: Python :: 3.8
Classifier: Programming Language :: Python :: 3.9
Classifier: Programming Language :: Python :: 3.10
Classifier: Programming Language :: Python :: 3.11
Requires-Python: >=3.8
License-File: LICENSE
Requires-Dist: requests>=2.31.0
Requires-Dist: python-dotenv>=1.0.0
Requires-Dist: rich>=13.7.0
Requires-Dist: typer>=0.9.0
Requires-Dist: gitignore-parser>=0.1.0
Requires-Dist: cerebras-cloud-sdk>=0.1.0
Requires-Dist: colorama>=0.4.4
Requires-Dist: pydantic>=2.0.0
Requires-Dist: click>=8.0.0
Requires-Dist: shellingham>=1.5.0
Dynamic: author
Dynamic: home-page
Dynamic: license-file
Dynamic: requires-python
